Workbook

Sheet Financial_KPI_Data
A1: Date | B1: Month | C1: Quarter | D1: Year | E1: Region | F1: Department | G1: Product Category | H1: Product Name | I1: Revenue | J1: Cost of Goods Sold | K1: Operating Expenses | L1: Gross Profit | M1: Net Profit | N1: Profit Margin % | O1: Sales Volume | P1: Budgeted Revenue | Q1: Actual Revenue | R1: Budget Variance | S1: Customer Segment | T1: Sales Channel
A2: 45619 | B2: November | C2: Q4 | D2: 2024 | E2: North | F2: Sales | G2: Apparel | H2: Women's Denim Jacket | I2: 10143.8 | J2: 3758.27 | K2: 2141.36 | L2: =I2-J2 -> 6385.53 | M2: =L2-K2 -> 4244.17 | N2: =IFERROR(M2/I2,0) -> 0.4184004 | O2: 134 | P2: 10281.86 | Q2: =I2 -> 10143.8 | R2: =Q2-P2 -> -138.06 | S2: Online Individual | T2: Direct Sales
A3: 45308 | B3: January | C3: Q1 | D3: 2024 | E3: North | F3: Sales | G3: Furniture | H3: Wooden Study Desk | I3: 76972.64 | J3: 35580.53 | K3: 15964.35 | L3: =I3-J3 -> 41392.11 | M3: =L3-K3 -> 25427.76 | N3: =IFERROR(M3/I3,0) -> 0.33034803 | O3: 278 | P3: 81621.59 | Q3: =I3 -> 76972.64 | R3: =Q3-P3 -> -4648.95 | S3: Government | T3: Retail Store
A4: 45521 | B4: August | C4: Q3 | D4: 2024 | E4: Central | F4: Operations | G4: Electronics | H4: Wireless Earbuds | I4: 74962.68 | J4: 30402.93 | K4: 9917.34 | L4: =I4-J4 -> 44559.75 | M4: =L4-K4 -> 34642.41 | N4: =IFERROR(M4/I4,0) -> 0.46212876 | O4: 377 | P4: 80888.35 | Q4: =I4 -> 74962.68 | R4: =Q4-P4 -> -5925.67 | S4: Retail | T4: Online
A5: 45486 | B5: July | C5: Q3 | D5: 2024 | E5: North | F5: Operations | G5: Apparel | H5: Casual T-Shirt | I5: 56745.5 | J5: 28142.72 | K5: 10238.83 | L5: =I5-J5 -> 28602.78 | M5: =L5-K5 -> 18363.95 | N5: =IFERROR(M5/I5,0) -> 0.32361949 | O5: 155 | P5: 64799.66 | Q5: =I5 -> 56745.5 | R5: =Q5-P5 -> -8054.16 | S5: Government | T5: Online
A6: 45574 | B6: October | C6: Q4 | D6: 2024 | E6: East | F6: IT | G6: Apparel | H6: Casual T-Shirt | I6: 37935.82 | J6: 13625.21 | K6: 5090.41 | L6: =I6-J6 -> 24310.61 | M6: =L6-K6 -> 19220.2 | N6: =IFERROR(M6/I6,0) -> 0.50665044 | O6: 118 | P6: 35538.9 | Q6: =I6 -> 37935.82 | R6: =Q6-P6 -> 2396.92 | S6: Retail | T6: Retail Store
A7: 45343 | B7: February | C7: Q1 | D7: 2024 | E7: West | F7: Operations | G7: Groceries | H7: Green Tea Pack | I7: 18131.09 | J7: 7105.6 | K7: 2539.2 | L7: =I7-J7 -> 11025.49 | M7: =L7-K7 -> 8486.29 | N7: =IFERROR(M7/I7,0) -> 0.46805184 | O7: 103 | P7: 20506.2 | Q7: =I7 -> 18131.09 | R7: =Q7-P7 -> -2375.11 | S7: Retail | T7: Retail Store
A8: 45565 | B8: September | C8: Q3 | D8: 2024 | E8: South | F8: Marketing | G8: Groceries | H8: Almonds 500g | I8: 70379.52 | J8: 33641.41 | K8: 12917.63 | L8: =I8-J8 -> 36738.11 | M8: =L8-K8 -> 23820.48 | N8: =IFERROR(M8/I8,0) -> 0.33845755 | O8: 158 | P8: 74277.44 | Q8: =I8 -> 70379.52 | R8: =Q8-P8 -> -3897.92 | S8: Retail | T8: Retail Store
A9: 45308 | B9: January | C9: Q1 | D9: 2024 | E9: East | F9: Finance | G9: Apparel | H9: Men's Formal Shirt | I9: 52762.88 | J9: 24452.22 | K9: 10958.17 | L9: =I9-J9 -> 28310.66 | M9: =L9-K9 -> 17352.49 | N9: =IFERROR(M9/I9,0) -> 0.32887685 | O9: 128 | P9: 48214.08 | Q9: =I9 -> 52762.88 | R9: =Q9-P9 -> 4548.8 | S9: Government | T9: Direct Sales
A10: 45621 | B10: November | C10: Q4 | D10: 2024 | E10: West | F10: Marketing | G10: Apparel | H10: Women's Denim Jacket | I10: 49504.22 | J10: 22662.81 | K10: 10497.47 | L10: =I10-J10 -> 26841.41 | M10: =L10-K10 -> 16343.94 | N10: =IFERROR(M10/I10,0) -> 0.33015246 | O10: 146 | P10: 48441.37 | Q10: =I10 -> 49504.22 | R10: =Q10-P10 -> 1062.85 | S10: Online Individual | T10: Direct Sales
A11: 45477 | B11: July | C11: Q3 | D11: 2024 | E11: South | F11: Marketing | G11: Home Appliances | H11: Vacuum Cleaner | I11: 22688.82 | J11: 11848.57 | K11: 2789.05 | L11: =I11-J11 -> 10840.25 | M11: =L11-K11 -> 8051.2 | N11: =IFERROR(M11/I11,0) -> 0.35485318 | O11: 66 | P11: 20374.44 | Q11: =I11 -> 22688.82 | R11: =Q11-P11 -> 2314.38 | S11: Government | T11: Online
A12: 45489 | B12: July | C12: Q3 | D12: 2024 | E12: West | F12: IT | G12: Groceries | H12: Whole Wheat Flour 5kg | I12: 64738.16 | J12: 33803.41 | K12: 6585.31 | L12: =I12-J12 -> 30934.75 | M12: =L12-K12 -> 24349.44 | N12: =IFERROR(M12/I12,0) -> 0.3761219 | O12: 148 | P12: 69024.9 | Q12: =I12 -> 64738.16 | R12: =Q12-P12 -> -4286.74 | S12: Online Individual | T12: Distributor
A13: 45620 | B13: November | C13: Q4 | D13: 2024 | E13: East | F13: Sales | G13: Apparel | H13: Winter Jacket | I13: 21237 | J13: 11484.19 | K13: 4913.77 | L13: =I13-J13 -> 9752.81 | M13: =L13-K13 -> 4839.04 | N13: =IFERROR(M13/I13,0) -> 0.22785893 | O13: 100 | P13: 19729.53 | Q13: =I13 -> 21237 | R13: =Q13-P13 -> 1507.47 | S13: Online Individual | T13: Retail Store
... A121: 45593 | B121: October | C121: Q4 | D121: 2024 | E121: West | F121: IT | G121: Electronics | H121: Smartwatch X2 | I121: 69736.05 | J121: 29142.88 | K121: 10457.64 | L121: =I121-J121 -> 40593.17 | M121: =L121-K121 -> 30135.53 | N121: =IFERROR(M121/I121,0) -> 0.43213704 | O121: 465 | P121: 62793.12 | Q121: =I121 -> 69736.05 | R121: =Q121-P121 -> 6942.93 | S121: Online Individual | T121: Online

Sheet KPI_Summary
A1: Financial KPI Monitoring & Profitability Dashboard — Summary KPIs
A3: KPI | B3: Value
A4: Total Revenue | B4: =SUM(Financial_KPI_Data!I2:I121) -> 6959601.8
A5: Total Cost of Goods Sold | B5: =SUM(Financial_KPI_Data!J2:J121) -> 3149977.7
A6: Total Operating Expenses | B6: =SUM(Financial_KPI_Data!K2:K121) -> 1204215.8
A7: Total Gross Profit | B7: =SUM(Financial_KPI_Data!L2:L121) -> 3809624.1
A8: Total Net Profit | B8: =SUM(Financial_KPI_Data!M2:M121) -> 2605408.3
A9: Overall Profit Margin % | B9: =IFERROR(B8/B4,0) -> 0.37436169
A10: Total Budgeted Revenue | B10: =SUM(Financial_KPI_Data!P2:P121) -> 7078105.2
A11: Total Actual Revenue | B11: =SUM(Financial_KPI_Data!Q2:Q121) -> 6959601.8
A12: Total Budget Variance | B12: =SUM(Financial_KPI_Data!R2:R121) -> -118503.44
A13: Total Sales Volume | B13: =SUM(Financial_KPI_Data!O2:O121) -> 28331
A14: Average Revenue per Transaction | B14: =IFERROR(B4/B15,0) -> 57996.681
A15: Number of Transactions | B15: =COUNTA(Financial_KPI_Data!A2:A121) -> 120
